{
  "Script main": {
    "prefix": "script main",
    "body": [
      "script main() -> Report {",
      "    ${1:value} = ${2:1 kW}",
      "    return plot line ${1:value}",
      "}"
    ],
    "description": "Create a main script that returns a report."
  },
  "Args struct": {
    "prefix": "struct Args",
    "body": [
      "struct Args {",
      "    ${1:input}: String = \"${2:data/sensor.csv}\"",
      "}"
    ],
    "description": "Create an Args struct with a default CSV path."
  },
  "CSV schema": {
    "prefix": "schema csv",
    "body": [
      "schema ${1:Sensor} {",
      "    ${2:time}: DateTime [iso8601]",
      "    ${3:T_supply}: AbsoluteTemperature [degC]",
      "    ${4:heat}: HeatRate [kW]",
      "}"
    ],
    "description": "Create a typed CSV schema."
  },
  "System model": {
    "prefix": "system thermal",
    "body": [
      "system ${1:Room} {",
      "    state ${2:T}: AbsoluteTemperature = ${3:20 degC}",
      "    parameter ${4:C}: HeatCapacity = ${5:1200 kJ/K}",
      "    parameter ${6:UA}: Conductance = ${7:250 W/K}",
      "    input ${8:T_out}: AbsoluteTemperature = ${9:10 degC}",
      "    input ${10:Q_internal}: HeatRate = ${11:500 W}",
      "    equation energy_balance:",
      "        ${4:C} * der(${2:T}) eq ${6:UA} * (${8:T_out} - ${2:T}) + ${10:Q_internal}",
      "}"
    ],
    "description": "Create the v1.0 first-order thermal system shape."
  },
  "Domain ports": {
    "prefix": "domain ports",
    "body": [
      "domain ${1:Thermal} package \"${2:eng.std.domains.thermal}\" version \"${3:0.1.0}\" {",
      "    across ${4:T}: AbsoluteTemperature [degC]",
      "    through ${5:Q}: HeatRate [kW]",
      "    conservation sum(${5:Q}) = 0",
      "}",
      "",
      "domain ${6:Fluid}[${7:Medium}] package \"${8:eng.std.domains.fluid}\" version \"${9:0.1.0}\" {",
      "    across ${10:height}: Length [m]",
      "    through ${11:m_dot}: MassFlowRate [kg/s]",
      "    conservation sum(${11:m_dot}) = 0",
      "}",
      "",
      "component ${12:RoomBoundary} {",
      "    port ${13:heat}: ${1:Thermal}",
      "}",
      "",
      "component ${14:SupplyPipe} {",
      "    port ${15:inlet}: ${6:Fluid}[${16:Water}]",
      "    port ${17:outlet}: ${6:Fluid}[${16:Water}]",
      "}",
      "",
      "connect ${14:SupplyPipe}.${15:inlet} -> ${14:SupplyPipe}.${17:outlet}"
    ],
    "description": "Create package/version domains, generic ports, and a compatible connection."
  },
  "Plot line": {
    "prefix": "plot line",
    "body": "return plot line ${1:series}",
    "description": "Return a line plot report."
  }
}
